authens/__init__.py
authens/apps.py
authens/backends.py
authens/conf.py
authens/forms.py
authens/models.py
authens/shortcuts.py
authens/signals.py
authens/urls.py
authens/utils.py
authens/views.py
authens/locale/en/LC_MESSAGES/django.mo
authens/locale/en/LC_MESSAGES/django.po
authens/migrations/0001_initial.py
authens/migrations/0002_old_cas_account.py
authens/migrations/__init__.py
authens/static/authens/css/authens.css
authens/templates/authens/base.html
authens/templates/authens/form_field_snippet.html
authens/templates/authens/form_full_snippet.html
authens/templates/authens/form_snippet.html
authens/templates/authens/login_switch.html
authens/templates/authens/oldcas_login.html
authens/templates/authens/pwd_login.html
authens/templates/authens/pwd_reset.html
authens/templates/authens/pwd_reset_confirm.html
authens/templates/authens/pwd_reset_email.txt
authens/templates/authens/pwd_reset_subject.txt
authens/tests/__init__.py
authens/tests/cas_utils.py
authens/tests/test_backend.py
authens/tests/test_shortcuts.py
authens/tests/test_views.py
authens-0.2.0.dist-info/LICENSE
authens-0.2.0.dist-info/METADATA
authens-0.2.0.dist-info/WHEEL
authens-0.2.0.dist-info/top_level.txt
authens-0.2.0.dist-info/RECORD
