Metadata-Version: 2.1
Name: authens
Version: 0.2.0
Summary: CAS Authentication Client at the ENS.
Author-email: Klub Dev ENS <klub-dev@ens.fr>, Tom Hubrecht <pypi@mail.hubrecht.ovh>
License: The MIT License (MIT)
Project-URL: Homepage, https://git.dgnum.eu/DGNum/authens
Project-URL: Repository, https://git.dgnum.eu/DGNum/authens
Project-URL: Issues, https://git.dgnum.eu/DGNum/authens/issues
Classifier: Development Status :: 4 - Beta
Classifier: Environment :: Web Environment
Classifier: Framework :: Django
Classifier: Framework :: Django :: 4.1
Classifier: Framework :: Django :: 4.2
Classifier: Intended Audience :: Developers
Classifier: License :: OSI Approved :: MIT License
Classifier: Operating System :: OS Independent
Classifier: Programming Language :: Python :: 3
Classifier: Programming Language :: Python :: 3 :: Only
Classifier: Programming Language :: Python :: 3.8
Classifier: Programming Language :: Python :: 3.9
Classifier: Programming Language :: Python :: 3.10
Classifier: Programming Language :: Python :: 3.11
Classifier: Programming Language :: Python :: 3.12
Classifier: Topic :: Internet :: WWW/HTTP
Classifier: Topic :: Internet :: WWW/HTTP :: Dynamic Content
License-File: LICENSE
Requires-Dist: django >=4.1
Requires-Dist: python-ldap <4,>=3
Requires-Dist: python-cas <2,>=1.5
